adhd/__init__.py
adhd-0.0.1.dist-info/METADATA
adhd-0.0.1.dist-info/WHEEL
adhd-0.0.1.dist-info/licenses/LICENSE
adhd-0.0.1.dist-info/RECORD
