Metadata-Version: 2.3
Name: adhd
Version: 0.0.1
Summary: adhd enhancing llm utilities // just focus on building.
Requires-Python: >=3.9
Requires-Dist: instructor>=1.7.0
Requires-Dist: litellm>=1.54.0
Requires-Dist: rich>=13.9.4
